README.md
setup.py
ajar/__init__.py
ajar/cli.py
ajar/config.py
ajar/db.py
ajar/version.py
ajar.egg-info/PKG-INFO
ajar.egg-info/SOURCES.txt
ajar.egg-info/dependency_links.txt
ajar.egg-info/entry_points.txt
ajar.egg-info/requires.txt
ajar.egg-info/top_level.txt