Metadata-Version: 2.1
Name: ajar
Version: 0.1
Summary: Auto generator for chess openings.
Home-page: https://github.com/bannsec/ajar
Author: Michael Bann
Author-email: self@bannsecurity.com
License: MIT
Keywords: chess stockfish opening generator
Platform: UNKNOWN
Classifier: Development Status :: 3 - Alpha
Classifier: Intended Audience :: End Users/Desktop
Classifier: License :: OSI Approved :: MIT License
Classifier: Programming Language :: Python :: 3
Classifier: Operating System :: POSIX :: Linux
Classifier: Environment :: Console
Provides-Extra: dev
